vsc/__init__.py
vsc/__main__.py
vsc/cli.py
vsc/compiler.py
vsc/config.py
vsc/exceptions.py
vsc/linker.py
vsc/optimizer.py
vsc/parser.py
vsc/server.py
vsc/utils.py
vsc/validator.py
vsc/valuascript.lark
vsc/functions/__init__.py
vsc/functions/core.py
vsc/functions/epidemiology.py
vsc/functions/financial.py
vsc/functions/io.py
vsc/functions/series.py
vsc/functions/statistics.py
vsc_toolchain-1.0.2.dist-info/METADATA
vsc_toolchain-1.0.2.dist-info/WHEEL
vsc_toolchain-1.0.2.dist-info/entry_points.txt
vsc_toolchain-1.0.2.dist-info/top_level.txt
vsc_toolchain-1.0.2.dist-info/RECORD
