Metadata-Version: 2.4
Name: vsc-toolchain
Version: 1.0.2
Summary: A compiler for the ValuaScript financial modeling language.
Home-page: https://github.com/Alessio2704/valuascript
Author: Alessio Marcuzzi
Author-email: alemarcuzzi03@gmail.com
Classifier: Programming Language :: Python :: 3.9
Classifier: License :: OSI Approved :: MIT License
Classifier: Operating System :: OS Independent
Requires-Python: >=3.9
Requires-Dist: lark
Requires-Dist: pandas
Requires-Dist: matplotlib
Requires-Dist: pygls>=1.0.0
Requires-Dist: lsprotocol
Provides-Extra: dev
Requires-Dist: pytest; extra == "dev"
Dynamic: author
Dynamic: author-email
Dynamic: classifier
Dynamic: description
Dynamic: description-content-type
Dynamic: home-page
Dynamic: provides-extra
Dynamic: requires-dist
Dynamic: requires-python
Dynamic: summary
